Metadata-Version: 2.1
Name: IIMIND
Version: 3897
Summary: A python port forwarding service using serveo pip3 install pycryptodome from IIMIND import *
Home-page: https://www.linkedin.com/in/neelanjanmanna/
Download-URL: https://github.com/user/reponame/archive/v_01.tar.gz
Author: Neelanjan Manna
Author-email: neelanjanmanna2021@gmail.com
License: MIT
Keywords: SOME,MEANINGFULL,KEYWORDS
Classifier: Development Status :: 3 - Alpha
Classifier: Intended Audience :: Developers
Classifier: Topic :: Software Development :: Build Tools
Classifier: License :: OSI Approved :: MIT License
Classifier: Programming Language :: Python :: 3.11
License-File: LICENSE.txt
